mustilib/__init__.py
mustilib-0.0.2.dist-info/LICENSE
mustilib-0.0.2.dist-info/METADATA
mustilib-0.0.2.dist-info/WHEEL
mustilib-0.0.2.dist-info/top_level.txt
mustilib-0.0.2.dist-info/RECORD
