Metadata-Version: 2.1
Name: mustilib
Version: 0.0.2
Summary: Package to reserve mustilib package name
Home-page: https://bitbucket.org/mustigroup/mustilib/src/master/
Author: MustiGroupIt
Author-email: it@mustigroup.com
License: UNKNOWN
Platform: UNKNOWN
Classifier: Programming Language :: Python :: 3
Classifier: License :: OSI Approved :: MIT License
Classifier: Operating System :: OS Independent
Requires-Python: >=3.6
